LICENCE.txt
MANIFEST.in
README.rst
setup.py
rstview/__init__.py
rstview/discover.py
rstview/html5writer.py
rstview/models.py
rstview/parser.py
rstview/registry.py
rstview/settings.py
rstview/views.py
rstview.egg-info/PKG-INFO
rstview.egg-info/SOURCES.txt
rstview.egg-info/dependency_links.txt
rstview.egg-info/not-zip-safe
rstview.egg-info/requires.txt
rstview.egg-info/top_level.txt
rstview/directives/__init__.py
rstview/directives/pygments_directive.py
rstview/templates/rstview/fileview.html
rstview/templatetags/__init__.py
rstview/templatetags/rstview_tags.py