Metadata-Version: 1.1
Name: rstview
Version: 0.4.0
Summary: 
